pjscript/__init__.py
pjscript/__main__.py
pjscript/interpreter.py
test/__init__.py
test/test_all.py
pjscript-0.0.4.dist-info/LICENSE
pjscript-0.0.4.dist-info/METADATA
pjscript-0.0.4.dist-info/WHEEL
pjscript-0.0.4.dist-info/top_level.txt
pjscript-0.0.4.dist-info/RECORD
