Metadata-Version: 2.1
Name: pjscript
Version: 0.0.4
Summary: JS like simple language LEXER, PARSER and INTERPRETER
Home-page: https://github.com/jay51/pjscript
Author: Jamal Al
Author-email: geenjay51@gmail.com
License: UNKNOWN
Platform: UNKNOWN
Classifier: Programming Language :: Python :: 3
Classifier: License :: OSI Approved :: MIT License
Classifier: Operating System :: OS Independent
Requires-Python: >=3.6
